streaming_data_types/__init__.py
streaming_data_types/_version.py
streaming_data_types/action_response_answ.py
streaming_data_types/alarm_al00.py
streaming_data_types/area_detector_ADAr.py
streaming_data_types/area_detector_NDAr.py
streaming_data_types/area_detector_ad00.py
streaming_data_types/array_1d_se00.py
streaming_data_types/dataarray_da00.py
streaming_data_types/epics_connection_ep01.py
streaming_data_types/epics_connection_info_ep00.py
streaming_data_types/eventdata_an44.py
streaming_data_types/eventdata_ev42.py
streaming_data_types/eventdata_ev43.py
streaming_data_types/eventdata_ev44.py
streaming_data_types/exceptions.py
streaming_data_types/finished_writing_wrdn.py
streaming_data_types/forwarder_config_update_fc00.py
streaming_data_types/forwarder_config_update_rf5k.py
streaming_data_types/histogram_hs00.py
streaming_data_types/histogram_hs01.py
streaming_data_types/json_json.py
streaming_data_types/logdata_f142.py
streaming_data_types/logdata_f144.py
streaming_data_types/nicos_cache_ns10.py
streaming_data_types/run_start_pl72.py
streaming_data_types/run_stop_6s4t.py
streaming_data_types/sample_environment_senv.py
streaming_data_types/status_x5f2.py
streaming_data_types/timestamps_tdct.py
streaming_data_types/utils.py
streaming_data_types/fbschemas/__init__.py
streaming_data_types/fbschemas/ADAr_ADArray_schema/ADArray.py
streaming_data_types/fbschemas/ADAr_ADArray_schema/Attribute.py
streaming_data_types/fbschemas/ADAr_ADArray_schema/DType.py
streaming_data_types/fbschemas/ADAr_ADArray_schema/__init__.py
streaming_data_types/fbschemas/NDAr_NDArray_schema/DType.py
streaming_data_types/fbschemas/NDAr_NDArray_schema/NDArray.py
streaming_data_types/fbschemas/NDAr_NDArray_schema/NDAttribute.py
streaming_data_types/fbschemas/NDAr_NDArray_schema/__init__.py
streaming_data_types/fbschemas/NDAr_NDArray_schema/epicsTimeStamp.py
streaming_data_types/fbschemas/action_response_answ/ActionOutcome.py
ess_streaming_data_types-0.27.0.dist-info/LICENSE
ess_streaming_data_types-0.27.0.dist-info/METADATA
ess_streaming_data_types-0.27.0.dist-info/WHEEL
ess_streaming_data_types-0.27.0.dist-info/top_level.txt
ess_streaming_data_types-0.27.0.dist-info/RECORD
