Metadata-Version: 2.1
Name: ess-streaming-data-types
Version: 0.27.0
Summary: Python utilities for handling ESS streamed data
Home-page: https://github.com/ess-dmsc/python-streaming-data-types
Author: ScreamingUdder
License: BSD 2-Clause License
Requires-Python: >=3.6.0
License-File: LICENSE
Requires-Dist: flatbuffers (>=22.11.23)
Requires-Dist: numpy
Provides-Extra: dev
Requires-Dist: flake8 ; extra == 'dev'
Requires-Dist: pre-commit ; extra == 'dev'
Requires-Dist: pytest ; extra == 'dev'
Requires-Dist: tox ; extra == 'dev'
